cifer/__init__.py
cifer/agent_ace.py
cifer/agent_ace_deleted.py
cifer/cli.py
cifer/client.py
cifer/config.py
cifer/connection_handler.py
cifer/connection_handler_wss.py
cifer/federated_pb2.py
cifer/federated_pb2_grpc.py
cifer/securetrain.py
cifer/server.py
cifer/setup.py
cifer/training.py
cifer/utils.py
cifer/datasets/__init__.py
cifer/datasets/custom.py
cifer/datasets/mnist.py
cifer/models/__init__.py
cifer/models/custom_model.py
cifer/models/default_model.py
cifer-1.0.25.dist-info/licenses/LICENSE
cifer-1.0.25.dist-info/METADATA
cifer-1.0.25.dist-info/WHEEL
cifer-1.0.25.dist-info/entry_points.txt
cifer-1.0.25.dist-info/top_level.txt
cifer-1.0.25.dist-info/RECORD
