Metadata-Version: 2.4
Name: cifer
Version: 1.0.25
Summary: Federated Learning and Fully Homomorphic Encryption
Home-page: https://github.com/cifer-ai/cifer
Author: Cifer.ai
Author-email: support@cifer.ai
Classifier: Programming Language :: Python :: 3
Classifier: License :: OSI Approved :: Apache Software License
Classifier: Operating System :: OS Independent
Classifier: Development Status :: 5 - Production/Stable
Classifier: Topic :: Scientific/Engineering :: Artificial Intelligence
Classifier: Topic :: Security :: Cryptography
Classifier: Framework :: Flask
Requires-Python: >=3.9
License-File: LICENSE
Requires-Dist: requests
Requires-Dist: tensorflow>=2.0
Requires-Dist: numpy
Requires-Dist: uvicorn
Requires-Dist: pydantic
Requires-Dist: PyJWT
Requires-Dist: websockets
Requires-Dist: argon2-cffi
Requires-Dist: h11
Requires-Dist: httpcore
Requires-Dist: idna
Requires-Dist: Jinja2
Requires-Dist: jsonschema
Requires-Dist: kiwisolver
Requires-Dist: MarkupSafe
Requires-Dist: matplotlib-inline
Requires-Dist: pandas
Requires-Dist: pillow
Requires-Dist: prometheus_client
Requires-Dist: psutil
Requires-Dist: pycryptodome
Requires-Dist: Pygments
Requires-Dist: python-dateutil
Requires-Dist: pytz
Requires-Dist: PyYAML
Requires-Dist: rich
Requires-Dist: six
Requires-Dist: sniffio
Requires-Dist: sympy
Requires-Dist: torch
Requires-Dist: torchvision
Requires-Dist: tornado
Requires-Dist: tqdm
Requires-Dist: typer
Requires-Dist: typing_extensions
Requires-Dist: tzdata
Requires-Dist: urllib3
Requires-Dist: nbclient
Requires-Dist: flask-cors
Requires-Dist: ipykernel
Requires-Dist: nbformat
Requires-Dist: websocket-client
Requires-Dist: notebook
Requires-Dist: fastapi
Requires-Dist: scikit-learn
Requires-Dist: joblib
Requires-Dist: phe
Requires-Dist: librosa
Requires-Dist: opencv-python
Requires-Dist: dgl
Requires-Dist: geopandas
Requires-Dist: open3d
Requires-Dist: pydicom
Requires-Dist: torchaudio
Requires-Dist: transformers
Requires-Dist: torch-geometric
Dynamic: author
Dynamic: author-email
Dynamic: classifier
Dynamic: description
Dynamic: description-content-type
Dynamic: home-page
Dynamic: license-file
Dynamic: requires-dist
Dynamic: requires-python
Dynamic: summary
